vision_aided_loss/DiffAugment_pytorch.py
vision_aided_loss/__init__.py
vision_aided_loss/blurpool.py
vision_aided_loss/cv_discriminator.py
vision_aided_loss/cv_losses.py
vision_aided_loss/cvmodel.py
vision_aided_loss/face_normals.py
vision_aided_loss/face_parsing.py
vision_aided_loss/resnet.py
vision_aided_loss/swintaskspecific.py
vision_aided_loss/utils_.py
vision_aided_loss/CLIP/__init__.py
vision_aided_loss/CLIP/clip/__init__.py
vision_aided_loss/CLIP/clip/clip.py
vision_aided_loss/CLIP/clip/model.py
vision_aided_loss-0.1.0.dist-info/LICENSE
vision_aided_loss-0.1.0.dist-info/METADATA
vision_aided_loss-0.1.0.dist-info/WHEEL
vision_aided_loss-0.1.0.dist-info/top_level.txt
vision_aided_loss-0.1.0.dist-info/RECORD
