Metadata-Version: 2.1
Name: vision-aided-loss
Version: 0.1.0
Summary: Vision-aided GAN training
Home-page: https://github.com/nupurkmr9/vision_aided_loss
Author: Nupur Kumari
Author-email: nupurkmr9@gmail.com
Classifier: Programming Language :: Python :: 3
Classifier: License :: OSI Approved :: BSD License
Classifier: Operating System :: OS Independent
License-File: LICENSE
Requires-Dist: torch (>=1.8.0)
Requires-Dist: torchvision (>=0.9.0)
Requires-Dist: numpy (>=1.14.3)
Requires-Dist: requests
Requires-Dist: timm
Requires-Dist: antialiased-cnns
Requires-Dist: gdown (==4.4.0)
Requires-Dist: ftfy
Requires-Dist: regex
Requires-Dist: tqdm
